pydanticonf/__init__.py
pydanticonf/py.typed
pydanticonf/settings.py
pydanticonf-1.0.0.dist-info/METADATA
pydanticonf-1.0.0.dist-info/WHEEL
pydanticonf-1.0.0.dist-info/RECORD
