Metadata-Version: 2.4
Name: pydanticonf
Version: 1.0.0
Summary: Pydantic settings with YAML configuration support.
Project-URL: Homepage, https://github.com/gao-hongnan/pydanticonf
Project-URL: Documentation, https://github.com/gao-hongnan/pydanticonf/tree/main/playbook
Project-URL: Repository, https://github.com/gao-hongnan/pydanticonf
Project-URL: Issues, https://github.com/gao-hongnan/pydanticonf/issues
Project-URL: Changelog, https://github.com/gao-hongnan/pydanticonf/releases
Author-email: GAO Hongnan <hongnangao@gmail.com>
Maintainer-email: GAO Hongnan <hongnangao@gmail.com>
License: Apache-2.0
Keywords: config,configuration,dotenv,environment,pydantic,settings,yaml
Classifier: Development Status :: 4 - Beta
Classifier: Intended Audience :: Developers
Classifier: License :: OSI Approved :: Apache Software License
Classifier: Operating System :: OS Independent
Classifier: Programming Language :: Python :: 3
Classifier: Programming Language :: Python :: 3.12
Classifier: Programming Language :: Python :: 3.13
Classifier: Topic :: Software Development :: Libraries
Classifier: Topic :: Software Development :: Libraries :: Python Modules
Classifier: Typing :: Typed
Requires-Python: >=3.12
Requires-Dist: pydantic-settings>=2.10.1
Requires-Dist: pydantic>=2.11.7
Requires-Dist: pyyaml>=6.0.2
Provides-Extra: playground
Requires-Dist: python-dotenv>=1.0.1; extra == 'playground'
Requires-Dist: rich>=13.12.0; extra == 'playground'
Requires-Dist: typer>=0.15.1; extra == 'playground'
